<?xml version="1.0" encoding="utf-8"?>
<Catalog>
    <CUnit id="AiurCityWarpGateAbandoned">
        <FlagArray index="Untargetable" value="0"/>
        <FlagArray index="IgnoreTerrainZInit" value="1"/>
        <EditorFlags index="NeutralDefault" value="0"/>
        <Collide index="RoachBurrow" value="0"/>
        <Attributes index="Armored" value="1"/>
        <LifeStart value="65536"/>
        <LifeMax value="65536"/>
        <LifeArmor value="0"/>
        <Height value="8"/>
        <AbilArray index="0" Link="OracleWeapon"/>
        <AbilArray index="1" Link="MedivacSpeedBoost"/>
        <AbilArray index="2" removed="1"/>
        <BehaviorArray index="0" removed="1"/>
        <BehaviorArray index="1" removed="1"/>
        <CardLayouts index="0">
            <LayoutButtons index="0" Face="OracleWeaponOff" AbilCmd="OracleWeapon,Off" Row="0" Column="0"/>
            <LayoutButtons index="1" Face="OracleWeaponOn" AbilCmd="OracleWeapon,On" Row="0" Column="1"/>
            <LayoutButtons index="2" removed="1"/>
        </CardLayouts>
        <Footprint value="Footprint4x4Contour"/>
        <PlacementFootprint value="Footprint4x4Contour"/>
        <RankDisplay value="Never"/>
    </CUnit>
    <CUnit id="Baneling">
        <LifeStart value="4"/>
        <LifeMax value="4"/>
        <LifeRegenRate value="0"/>
        <Speed value="25"/>
        <Food value="0"/>
        <CostResource index="Minerals" value="0"/>
        <CostResource index="Vespene" value="0"/>
        <AbilArray index="3" Link="AttackAllowsInvulnerable"/>
        <AbilArray index="4" removed="1"/>
        <AbilArray index="5" removed="1"/>
        <AbilArray index="6" removed="1"/>
        <CardLayouts index="0">
            <LayoutButtons index="6" Face="AttackAllowsInvulnerable" Type="AbilCmd" AbilCmd="AttackAllowsInvulnerable,Execute" Row="1" Column="4"/>
            <LayoutButtons index="7" removed="1"/>
            <LayoutButtons index="8" removed="1"/>
            <LayoutButtons index="9" removed="1"/>
            <LayoutButtons index="10" removed="1"/>
            <LayoutButtons index="11" removed="1"/>
            <LayoutButtons index="12" removed="1"/>
            <LayoutButtons index="13" removed="1"/>
        </CardLayouts>
        <TauntDuration index="Cheer" value="4"/>
        <TauntDuration index="Dance" value="4"/>
        <ScoreMake value="0"/>
        <ScoreKill value="0"/>
        <WeaponArray index="0" Link="VolatileBurst"/>
        <WeaponArray index="1" removed="1"/>
        <BehaviorArray index="0" removed="1"/>
        <EquipmentArray index="0" removed="1"/>
        <Acceleration value="800"/>
        <ShieldDamageRatio value="1024"/>
        <KillDisplay value="Never"/>
        <RankDisplay value="Never"/>
        <LateralAcceleration value="800"/>
        <StationaryTurningRate value="1440"/>
        <TurningRate value="1440"/>
    </CUnit>
    <!--CUnit id="ArtanisVoidAiur6">-->
    <!--        <DeathRevealRadius value="3"/>-->
    <!--        <Race value="Prot"/>-->
    <!--        <Mob value="Multiplayer"/>-->
    <!--        <FlagArray index="PreventDestroy" value="1"/>-->
    <!--        <FlagArray index="UseLineOfSight" value="1"/>-->
    <!--        <FlagArray index="AlwaysThreatens" value="1"/>-->
    <!--        <FlagArray index="AIThreatGround" value="1"/>-->
    <!--        <FlagArray index="AIThreatAir" value="1"/>-->
    <!--        <FlagArray index="AISplash" value="1"/>-->
    <!--        <FlagArray index="AIHighPrioTarget" value="1"/>-->
    <!--        <FlagArray index="AICaster" value="1"/>-->
    <!--        <FlagArray index="AIPressForwardDisabled" value="1"/>-->
    <!--        <FlagArray index="ArmySelect" value="1"/>-->
    <!--        <PlaneArray index="Ground" value="1"/>-->
    <!--        <Collide index="Ground" value="1"/>-->
    <!--        <Collide index="Small" value="1"/>-->
    <!--        <Collide index="ForceField" value="1"/>-->
    <!--        <Attributes index="Biological" value="1"/>-->
    <!--        <Attributes index="Psionic" value="1"/>-->
    <!--        <Attributes index="Heroic" value="1"/>-->
    <!--        <LifeStart value="200"/>-->
    <!--        <LifeMax value="200"/>-->
    <!--        <LifeArmor value="2"/>-->
    <!--        <LifeRegenRate value="1"/>-->
    <!--        <LifeArmorName value="Unit/LifeArmorName/ProtossArmor"/>-->
    <!--        <EnergyStart value="200"/>-->
    <!--        <EnergyMax value="200"/>-->
    <!--        <EnergyRegenRate value="2.25"/>-->
    <!--        <ShieldsStart value="500"/>-->
    <!--        <ShieldsMax value="500"/>-->
    <!--        <ShieldRegenDelay value="10"/>-->
    <!--        <ShieldRegenRate value="4"/>-->
    <!--        <ShieldArmorName value="Unit/ShieldArmorName/ProtossPlasmaShields"/>-->
    <!--        <Speed value="2.9492"/>-->
    <!--        <Acceleration value="1000"/>-->
    <!--        <Deceleration value="1000"/>-->
    <!--        <LateralAcceleration value="46"/>-->
    <!--        <StationaryTurningRate value="999.8437"/>-->
    <!--        <TurningRate value="999.8437"/>-->
    <!--        <Sight value="10"/>-->
    <!--        <CostCategory value="Army"/>-->
    <!--        <AttackTargetPriority value="20"/>-->
    <!--        <DamageDealtXP value="1"/>-->
    <!--        <DamageTakenXP value="1"/>-->
    <!--        <KillXP value="40"/>-->
    <!--        <AbilArray Link="stop"/>-->
    <!--        <AbilArray Link="move"/>-->
    <!--        <AbilArray Link="attack"/>-->
    <!--        <AbilArray Link="Warpable"/>-->
    <!--        <AbilArray Link="ProgressRally"/>-->
    <!--        <AbilArray Link="ArtanisAstralWind"/>-->
    <!--        <AbilArray Link="ArtanisChannel"/>-->
    <!--        <AbilArray Link="ArtanisVoidPsiStorm"/>-->
    <!--        <AbilArray Link="EnergyChannel"/>-->
    <!--        <BehaviorArray Link="ArtanisPremonition"/>-->
    <!--        <WeaponArray Link="ArtanisVoidUlnar"/>-->
    <!--        <CardLayouts>-->
    <!--            <LayoutButtons Face="MoveChampions" Type="AbilCmd" AbilCmd="move,Move" Row="0" Column="0"/>-->
    <!--            <LayoutButtons Face="Stop" Type="AbilCmd" AbilCmd="stop,Stop" Row="0" Column="1"/>-->
    <!--            <LayoutButtons Face="MoveHoldPosition" Type="AbilCmd" AbilCmd="move,HoldPos" Row="0" Column="2"/>-->
    <!--            <LayoutButtons Face="MovePatrol" Type="AbilCmd" AbilCmd="move,Patrol" Row="0" Column="3"/>-->
    <!--            <LayoutButtons Face="AttackChampions" Type="AbilCmd" AbilCmd="attack,Execute" Row="0" Column="4"/>-->
    <!--            <LayoutButtons Face="Rally" Type="AbilCmd" AbilCmd="ProgressRally,Rally1" Row="2" Column="4"/>-->
    <!--            <LayoutButtons Face="PsionicSuperStorm" Type="AbilCmd" AbilCmd="ArtanisVoidPsiStorm,Execute" Row="2" Column="0"/>-->
    <!--            <LayoutButtons Face="ArtanisPremonition" Type="Passive" Row="2" Column="1"/>-->
    <!--            <LayoutButtons Face="ArtanisAstralWind" Type="AbilCmd" AbilCmd="ArtanisAstralWind,Execute" Row="2" Column="2"/>-->
    <!--            <LayoutButtons Face="ArtanisForceOfWill" Type="Passive" Row="2" Column="3"/>-->
    <!--        </CardLayouts>-->
    <!--        <CardLayouts>-->
    <!--            <LayoutButtons Face="ArtanisChannel" Type="AbilCmd" AbilCmd="ArtanisChannel,On" Row="1" Column="2"/>-->
    <!--            <LayoutButtons Face="ArtanisChannelOff" Type="AbilCmd" AbilCmd="ArtanisChannel,Off" Row="1" Column="3"/>-->
    <!--        </CardLayouts>-->
    <!--        <Radius value="0.375"/>-->
    <!--        <SeparationRadius value="0.375"/>-->
    <!--        <InnerRadius value="0.375"/>-->
    <!--        <CargoSize value="2"/>-->
    <!--        <ScoreMake value="200"/>-->
    <!--        <ScoreKill value="200"/>-->
    <!--        <ScoreResult value="BuildOrder"/>-->
    <!--        <SubgroupPriority value="29"/>-->
    <!--        <MinimapRadius value="0.375"/>-->
    <!--        <EditorCategories value="ObjectType:Hero,ObjectFamily:Campaign"/>-->
    <!--        <AIEvalFactor value="1.8"/>-->
    <!--        <GlossaryCategory value="Unit/Category/ProtossStory"/>-->
    <!--        <GlossaryPriority value="80"/>-->
    <!--        <GlossaryStrongArray value="Marine"/>-->
    <!--        <GlossaryStrongArray value="Stalker"/>-->
    <!--        <GlossaryStrongArray value="Hydralisk"/>-->
    <!--        <GlossaryWeakArray value="Ghost"/>-->
    <!--        <GlossaryWeakArray value="Zealot"/>-->
    <!--        <GlossaryWeakArray value="Roach"/>-->
    <!--        <HotkeyCategory value="Unit/Category/ProtossStory"/>-->
    <!--        <KillDisplay value="Always"/>-->
    <!--        <RankDisplay value="Always"/>-->
    <!--        <TauntDuration index="Cheer" value="5"/>-->
    <!--        <TauntDuration index="Dance" value="5"/>-->
    <!--        <AlliedPushPriority value="11"/>-->
    <!--    </CUnit-->
    <CUnit id="Banshee">
        <FlagArray index="Unselectable" value="1"/>
        <FlagArray index="Untargetable" value="1"/>
        <FlagArray index="Uncursorable" value="1"/>
        <FlagArray index="Invulnerable" value="1"/>
        <Collide index="Flying" value="0"/>
        <Attributes index="Psionic" value="1"/>
        <Attributes index="Structure" value="1"/>
        <Speed value="160"/>
        <Acceleration value="1000"/>
        <Height value="1.5"/>
        <BehaviorArray index="0" Link="TimeScale10"/>
        <BehaviorArray index="1" removed="1"/>
        <BehaviorArray index="2" removed="1"/>
        <WeaponArray index="0" removed="1"/>
    </CUnit>
    <CUnit id="Beacon_Protoss">
        <FlagArray index="Unselectable" value="1"/>
        <Attributes index="Psionic" value="1"/>
    </CUnit>
    <CUnit id="Beacon_Terran">
        <FlagArray index="Unselectable" value="1"/>
        <Attributes index="Biological" value="1"/>
    </CUnit>
    <CUnit id="Beacon_Zerg">
        <FlagArray index="Unselectable" value="1"/>
        <Attributes index="Biological" value="1"/>
        <Attributes index="Psionic" value="1"/>
    </CUnit>
    <CUnit id="Bunker">
        <FlagArray index="Invulnerable" value="1"/>
        <FlagArray index="ArmorDisabledWhileConstructing" value="0"/>
        <Attributes index="Armored" value="0"/>
        <Attributes index="Mechanical" value="0"/>
        <LifeStart value="1024"/>
        <LifeMax value="1024"/>
        <LifeArmor value="0"/>
        <ShieldsStart value="1024"/>
        <ShieldsMax value="1024"/>
        <ShieldRegenRate value="0.0625"/>
        <ShieldDamageRatio value="1024"/>
        <CostResource index="Minerals" value="0"/>
        <AbilArray index="1" Link="stop"/>
        <AbilArray index="2" Link="attack"/>
        <AbilArray index="3" Link="PrologueVoidArmor"/>
        <AbilArray index="4" Link="PrologueVoidArmor2"/>
        <AbilArray index="5" removed="1"/>
        <AbilArray index="6" removed="1"/>
        <AbilArray index="7" removed="1"/>
        <AbilArray index="8" removed="1"/>
        <AbilArray index="9" removed="1"/>
        <AbilArray index="10" removed="1"/>
        <AbilArray index="11" removed="1"/>
        <AbilArray index="12" removed="1"/>
        <AbilArray index="13" removed="1"/>
        <AbilArray index="14" removed="1"/>
        <BehaviorArray index="0" Link="DamageBASELINE"/>
        <BehaviorArray index="1" Link="DamageUP"/>
        <BehaviorArray index="2" removed="1"/>
        <BehaviorArray index="3" removed="1"/>
        <BehaviorArray index="4" removed="1"/>
        <BehaviorArray index="5" removed="1"/>
        <BehaviorArray index="6" removed="1"/>
        <CardLayouts index="0">
            <LayoutButtons index="0" Face="CancelBuilding" AbilCmd="BuildInProgress,Cancel" Row="2"/>
            <LayoutButtons index="1" AbilCmd="stop,Stop"/>
            <LayoutButtons index="2" Face="AttackBuilding" AbilCmd="attack,Execute" Row="0" Column="4"/>
            <LayoutButtons index="3" Face="PrologueVoidArmor" AbilCmd="PrologueVoidArmor,Execute"/>
            <LayoutButtons index="4" Face="PrologueVoidArmor2" AbilCmd="PrologueVoidArmor2,Execute" Row="2" Column="1"/>
            <LayoutButtons index="5" removed="1"/>
            <LayoutButtons index="6" removed="1"/>
            <LayoutButtons index="7" removed="1"/>
            <LayoutButtons index="8" removed="1"/>
            <LayoutButtons index="9" removed="1"/>
            <LayoutButtons index="10" removed="1"/>
            <LayoutButtons index="11" removed="1"/>
            <LayoutButtons index="12" removed="1"/>
            <LayoutButtons index="13" removed="1"/>
            <LayoutButtons index="14" removed="1"/>
            <LayoutButtons index="15" removed="1"/>
            <LayoutButtons index="16" removed="1"/>
            <LayoutButtons index="17" removed="1"/>
            <LayoutButtons index="18" removed="1"/>
            <LayoutButtons index="19" removed="1"/>
        </CardLayouts>
        <ScoreMake value="0"/>
        <ScoreKill value="0"/>
        <TurretArray value="FreeRotate"/>
        <WeaponArray index="0" Link="PunisherGrenades" Turret="FreeRotate"/>
        <WeaponArray index="1" removed="1"/>
        <Sight value="16"/>
        <Footprint value="Footprint3x3"/>
    </CUnit>
    <CUnit id="CommandCenter">
        <FlagArray index="Invulnerable" value="1"/>
        <EnergyStart value="0"/>
        <Food value="0"/>
        <CostResource index="Minerals" value="0"/>
        <AbilArray index="1" Link="stop"/>
        <AbilArray index="2" Link="attack"/>
        <AbilArray index="3" Link="PrologueVoidArmor"/>
        <AbilArray index="4" Link="PrologueVoidArmor2"/>
        <AbilArray index="5" removed="1"/>
        <AbilArray index="6" removed="1"/>
        <AbilArray index="7" removed="1"/>
        <AbilArray index="8" removed="1"/>
        <AbilArray index="9" removed="1"/>
        <BehaviorArray index="0" Link="DamageBASELINE"/>
        <BehaviorArray index="1" Link="DamageUP"/>
        <BehaviorArray index="2" removed="1"/>
        <BehaviorArray index="3" removed="1"/>
        <BehaviorArray index="4" removed="1"/>
        <BehaviorArray index="5" removed="1"/>
        <Footprint value="Footprint4x4"/>
        <PlacementFootprint value="Footprint4x4"/>
        <Attributes index="Armored" value="0"/>
        <Attributes index="Mechanical" value="0"/>
        <CardLayouts index="0">
            <LayoutButtons index="0" Face="CancelBuilding" AbilCmd="BuildInProgress,Cancel" Row="2" Column="4"/>
            <LayoutButtons index="1" Face="Stop" AbilCmd="stop,Stop" Row="0" Column="1"/>
            <LayoutButtons index="2" Face="AttackBuilding" AbilCmd="attack,Execute"/>
            <LayoutButtons index="3" Face="PrologueVoidArmor" AbilCmd="PrologueVoidArmor,Execute" Row="2" Column="0"/>
            <LayoutButtons index="4" Face="PrologueVoidArmor2" AbilCmd="PrologueVoidArmor2,Execute" Column="1"/>
            <LayoutButtons index="5" removed="1"/>
            <LayoutButtons index="6" removed="1"/>
            <LayoutButtons index="7" removed="1"/>
            <LayoutButtons index="8" removed="1"/>
            <LayoutButtons index="9" removed="1"/>
            <LayoutButtons index="10" removed="1"/>
            <LayoutButtons index="11" removed="1"/>
            <LayoutButtons index="12" removed="1"/>
            <LayoutButtons index="13" removed="1"/>
        </CardLayouts>
        <EquipmentArray Weapon="ATSLaserBattery"/>
    </CUnit>
    <CUnit id="HERCCompound">
        <FlagArray index="Untargetable" value="1"/>
        <FlagArray index="Invulnerable" value="1"/>
        <Attributes index="Mechanical" value="0"/>
        <LifeStart value="99999"/>
        <LifeMax value="99999"/>
        <LifeArmor value="99999"/>
        <AbilArray index="1" Link="que1"/>
        <AbilArray index="2" Link="ForgeResearch"/>
        <AbilArray index="3" removed="1"/>
        <CardLayouts index="0">
            <LayoutButtons index="0" Face="Cancel" AbilCmd="que1,CancelLast" Row="2" Column="4"/>
            <LayoutButtons index="1" Face="ResearchNeosteelFrame" Type="AbilCmd" AbilCmd="ForgeResearch,Research11" Row="0" Column="0"/>
            <LayoutButtons index="2" removed="1"/>
            <LayoutButtons index="3" removed="1"/>
            <LayoutButtons index="4" removed="1"/>
        </CardLayouts>
        <Footprint value="Footprint1x1Contour"/>
        <PlacementFootprint value="Footprint1x1"/>
    </CUnit>
    <CUnit id="InfestedSupply">
        <Attributes index="Light" value="0"/>
        <Attributes index="Biological" value="0"/>
        <Attributes index="Psionic" value="1"/>
        <LifeStart value="65536"/>
        <LifeMax value="65536"/>
        <LifeArmor value="0"/>
        <LifeRegenRate value="4"/>
        <ScoreMake value="0"/>
        <ScoreKill value="0"/>
        <FlagArray index="Unselectable" value="1"/>
        <FlagArray index="Uncursorable" value="1"/>
        <FlagArray index="Invulnerable" value="1"/>
        <Footprint value="Footprint2x2ContourBASE"/>
    </CUnit>
    <CUnit id="PhotonCannon">
        <FlagArray index="UseLineOfSight" value="0"/>
        <FlagArray index="Invulnerable" value="1"/>
        <FlagArray index="ArmorDisabledWhileConstructing" value="0"/>
        <FlagArray index="VisionTestCenterOnly" value="1"/>
        <LifeStart value="4"/>
        <LifeMax value="4"/>
        <LifeArmor value="0"/>
        <ShieldsStart value="4"/>
        <ShieldsMax value="4"/>
        <ShieldRegenDelay value="0"/>
        <ShieldRegenRate value="4"/>
        <Sight value="16"/>
        <CostResource index="Minerals" value="0"/>
        <BehaviorArray index="0" Link="DamageBASELINE"/>
        <BehaviorArray index="1" Link="DamageUP"/>
        <BehaviorArray index="2" removed="1"/>
        <CardLayouts index="0">
            <LayoutButtons index="3" Face="PrologueVoidArmor" Type="AbilCmd" AbilCmd="PrologueVoidArmor,Execute" Requirements="" Column="0"/>
            <LayoutButtons Face="PrologueVoidArmor2" Type="AbilCmd" AbilCmd="PrologueVoidArmor2,Execute" Row="2" Column="1"/>
        </CardLayouts>
        <Footprint value="Footprint2x2"/>
        <ScoreMake value="0"/>
        <ScoreKill value="0"/>
        <Attributes index="Armored" value="0"/>
        <AbilArray Link="PrologueVoidArmor"/>
        <AbilArray Link="PrologueVoidArmor2"/>
    </CUnit>
    <CUnit id="PsiDisruptor">
        <FlagArray index="UseLineOfSight" value="0"/>
        <FlagArray index="Invulnerable" value="1"/>
        <Attributes index="Armored" value="0"/>
        <Attributes index="Mechanical" value="0"/>
        <LifeStart value="65536"/>
        <LifeMax value="65536"/>
        <Sight value="8"/>
        <CostResource index="Minerals" value="0"/>
        <CostResource index="Vespene" value="0"/>
        <AbilArray Link="stop"/>
        <AbilArray Link="attack"/>
        <AbilArray Link="PrologueVoidArmor"/>
        <AbilArray Link="PrologueVoidArmor2"/>
        <BehaviorArray index="0" Link="DamageBASELINE"/>
        <BehaviorArray index="1" Link="DamageUP"/>
        <BehaviorArray index="2" Link="VoodooShield"/>
        <TurretArray value="FreeRotate"/>
        <WeaponArray Link="SupershieldWeapon" Turret="FreeRotate"/>
        <CardLayouts index="0">
            <LayoutButtons index="0" Face="CancelBuilding"/>
            <LayoutButtons index="1" Face="Stop" Type="AbilCmd" AbilCmd="stop,Stop" Row="0" Column="1"/>
            <LayoutButtons Face="AttackBuilding" Type="AbilCmd" AbilCmd="attack,Execute" Row="0" Column="4"/>
            <LayoutButtons Face="PrologueVoidArmor" Type="AbilCmd" AbilCmd="PrologueVoidArmor,Execute" Row="2" Column="0"/>
            <LayoutButtons Face="PrologueVoidArmor2" Type="AbilCmd" AbilCmd="PrologueVoidArmor2,Execute" Row="2" Column="1"/>
        </CardLayouts>
        <Footprint value="Footprint2x2"/>
        <ScoreMake value="0"/>
        <ScoreKill value="0"/>
    </CUnit>
    <CUnit id="Pylon">
        <FlagArray index="Invulnerable" value="1"/>
        <Attributes index="Armored" value="0"/>
        <LifeStart value="64"/>
        <LifeMax value="64"/>
        <LifeArmor value="0"/>
        <ShieldsStart value="4"/>
        <ShieldsMax value="4"/>
        <ShieldRegenDelay value="0"/>
        <ShieldRegenRate value="1"/>
        <ShieldDamageRatio value="16"/>
        <Sight value="32"/>
        <Food value="0"/>
        <CostResource index="Minerals" value="0"/>
        <AbilArray index="1" Link="stop"/>
        <AbilArray index="2" Link="attack"/>
        <AbilArray Link="PrologueVoidArmor"/>
        <AbilArray Link="PrologueVoidArmor2"/>
        <BehaviorArray index="0" Link="DamageBASELINE"/>
        <BehaviorArray index="1" Link="DamageUP"/>
        <TurretArray value="FreeRotate"/>
        <WeaponArray Link="MothershipBeam" Turret="FreeRotate"/>
        <CardLayouts index="0">
            <LayoutButtons index="1" AbilCmd="stop,Stop" Column="1"/>
            <LayoutButtons index="2" Face="AttackBuilding" AbilCmd="attack,Execute"/>
            <LayoutButtons index="3" Face="PrologueVoidArmor" Type="AbilCmd" AbilCmd="PrologueVoidArmor,Execute" Requirements=""/>
            <LayoutButtons Face="PrologueVoidArmor2" Type="AbilCmd" AbilCmd="PrologueVoidArmor2,Execute" Row="2" Column="1"/>
        </CardLayouts>
        <Footprint value="Footprint1x1"/>
        <ScoreMake value="0"/>
        <ScoreKill value="0"/>
        <PlacementFootprint value="Footprint1x1"/>
        <!--EnergyStart value="50"/>
        <EnergyMax value="200"/>
        <EnergyRegenRate value="0.5625"/>
        <AbilArray Link="PylonShieldRecharge"/>
        <CardLayouts index="0">
            <LayoutButtons Face="Repair" Type="AbilCmd" AbilCmd="PylonShieldRecharge,Execute" Row="2" Column="0"/>
        </CardLayouts>
        <PowerupEffect value="PylonShieldRechargePersistent"/>
        <PowerupRange value="7"/-->
    </CUnit>
    <CUnit id="Replicant">
        <LifeStart value="65536"/>
        <LifeMax value="65536"/>
        <LifeRegenRate value="65536"/>
        <ShieldsStart value="65536"/>
        <ShieldsMax value="65536"/>
        <ShieldRegenRate value="65536"/>
        <ShieldDamageRatio value="65536"/>
        <AbilArray index="4" Link="ProgressRally"/>
        <AbilArray index="5" removed="1"/>
        <WeaponArray index="0" removed="1"/>
        <CardLayouts index="0">
            <LayoutButtons index="6" removed="1"/>
        </CardLayouts>
    </CUnit>
    <CUnit id="SJMercAATower">
        <FlagArray index="Invulnerable" value="1"/>
        <Attributes index="Armored" value="0"/>
        <Attributes index="Mechanical" value="0"/>
        <Height value="32"/>
        <CostResource index="Minerals" value="0"/>
        <BehaviorArray Link="OrbitalDelay"/>
        <WeaponArray index="0" Link="ATSLaserBattery"/>
    </CUnit>
    <CUnit id="Sentry">
        <FlagArray index="Worker" value="1"/>
        <FlagArray index="UseLineOfSight" value="0"/>
        <FlagArray index="KillCredit" value="0"/>
        <Attributes index="Light" value="0"/>
        <Attributes index="Armored" value="1"/>
        <Attributes index="Mechanical" value="0"/>
        <Attributes index="Psionic" value="0"/>
        <LifeStart value="8"/>
        <LifeMax value="8"/>
        <LifeArmor value="0"/>
        <EnergyStart value="0"/>
        <EnergyMax value="0"/>
        <EnergyRegenDelay value="32"/>
        <EnergyRegenRate value="0"/>
        <ShieldsStart value="64"/>
        <ShieldsMax value="64"/>
        <ShieldArmor value="1"/>
        <ShieldRegenDelay value="64"/>
        <ShieldRegenRate value="32"/>
        <Speed value="4"/>
        <Food value="0"/>
        <CostResource index="Minerals" value="256"/>
        <CostResource index="Vespene" value="0"/>
        <AbilArray index="4" Link="ProgressRally"/>
        <AbilArray index="5" Link="BuildInProgress"/>
        <AbilArray index="6" Link="ProtossBuild"/>
        <AbilArray index="7" Link="ZeratulBlink"/>
        <AbilArray index="8" Link="TerranBuild"/>
        <AbilArray index="9" Link="TimeWarp"/>
        <AbilArray index="10" Link="que1"/>
        <AbilArray index="11" removed="1"/>
        <AbilArray index="12" removed="1"/>
        <AbilArray index="13" removed="1"/>
        <AbilArray index="14" removed="1"/>
        <AbilArray index="15" removed="1"/>
        <AbilArray index="16" removed="1"/>
        <AbilArray index="17" removed="1"/>
        <AbilArray index="18" removed="1"/>
        <AbilArray index="19" removed="1"/>
        <AbilArray index="20" removed="1"/>
        <AbilArray index="21" removed="1"/>
        <WeaponArray index="0" removed="1"/>
        <CardLayouts index="0">
            <LayoutButtons index="4" Face="" Type="Undefined" AbilCmd="" Column="0"/>
            <LayoutButtons index="5" Face="" Type="Undefined" AbilCmd="" Row="0" Column="0"/>
            <LayoutButtons index="6" Face="" Type="Undefined" AbilCmd="" Row="0"/>
            <LayoutButtons index="7" Face="" Type="Undefined" AbilCmd="" Row="0" Column="0"/>
            <LayoutButtons index="8" Face="" Type="Undefined" AbilCmd="" Row="0"/>
            <LayoutButtons index="9">
                <Face value=""/>
                <Type value="Undefined"/>
                <AbilCmd value=""/>
                <Requirements value=""/>
                <SubmenuCardId value=""/>
                <SubmenuFullSubCmdValidation value="0"/>
                <Row value="0"/>
            </LayoutButtons>
            <LayoutButtons Row="0" Column="0"/>
            <LayoutButtons Row="0" Column="0"/>
            <LayoutButtons Row="0" Column="0"/>
            <LayoutButtons Row="0" Column="0"/>
            <LayoutButtons>
                <Face value="ProtossBuild"/>
                <Type value="Submenu"/>
                <SubmenuCardId value="0002"/>
                <SubmenuIsSticky value="1"/>
                <Row value="2"/>
                <Column value="0"/>
            </LayoutButtons>
            <LayoutButtons Face="Blink" Type="AbilCmd" AbilCmd="ZeratulBlink,Execute" Row="2" Column="1"/>
        </CardLayouts>
        <CardLayouts index="1" CardId="0002">
            <LayoutButtons index="0" Face="FleetBeacon" AbilCmd="ProtossBuild,Build6" Column="2"/>
            <LayoutButtons index="1" Face="PhotonCannon" AbilCmd="ProtossBuild,Build8" Column="0"/>
            <LayoutButtons index="2" Face="SOAProxyPylon" AbilCmd="ProtossBuild,Build14" Column="1"/>
            <LayoutButtons index="3" Face="Bunker" AbilCmd="TerranBuild,Build7" Row="1" Column="0"/>
            <LayoutButtons index="4" Face="CommandCenterOrbRelay" AbilCmd="TerranBuild,Build21" Column="1"/>
            <LayoutButtons index="5" Face="PsiDisruptor" AbilCmd="TerranBuild,Build8" Column="2"/>
            <LayoutButtons index="6" removed="1"/>
            <LayoutButtons index="7" removed="1"/>
            <LayoutButtons index="8" removed="1"/>
            <LayoutButtons index="9" removed="1"/>
            <LayoutButtons index="10" removed="1"/>
            <LayoutButtons index="11" removed="1"/>
            <LayoutButtons index="12" removed="1"/>
            <LayoutButtons index="13" removed="1"/>
        </CardLayouts>
        <CardLayouts CardId="0003">
            <LayoutButtons Face="ProtossShieldsLevel1" Type="AbilCmd" AbilCmd="ForgeResearch,Research7" Row="0" Column="0"/>
            <LayoutButtons Face="ProtossGroundWeaponsLevel1" Type="AbilCmd" AbilCmd="ForgeResearch,Research1" Row="0" Column="1"/>
            <LayoutButtons Face="ProtossAirWeaponsLevel1" Type="AbilCmd" AbilCmd="ForgeResearch,Research4" Row="0" Column="2"/>
            <LayoutButtons Face="TerranInfantryWeaponsLevel1" Type="AbilCmd" AbilCmd="ForgeResearch,Research12" Row="0" Column="3"/>
            <LayoutButtons Face="ResearchNeosteelFrame" Type="AbilCmd" AbilCmd="ForgeResearch,Research11" Row="0" Column="4"/>
        </CardLayouts>
        <InnerRadius value="0"/>
        <KillDisplay value="Never"/>
        <RankDisplay value="Never"/>
        <PlaneArray index="Ground" value="0"/>
        <PlaneArray index="Air" value="1"/>
        <Collide index="Ground" value="0"/>
        <Collide index="ForceField" value="0"/>
        <Collide index="Locust" value="0"/>
        <Collide index="Flying" value="1"/>
        <Mover value="Fly"/>
        <Radius value="0"/>
    </CUnit>
    <CUnit id="ShieldBattery">
        <FlagArray index="Invulnerable" value="1"/>
        <Attributes index="Armored" value="0"/>
        <LifeStart value="256"/>
        <LifeMax value="256"/>
        <LifeArmor value="0"/>
        <EnergyStart value="0"/>
        <EnergyMax value="0"/>
        <ShieldsStart value="1"/>
        <ShieldsMax value="1"/>
        <ShieldRegenDelay value="0"/>
        <ShieldRegenRate value="0.125"/>
        <ShieldDamageRatio value="256"/>
        <CostResource index="Minerals" value="0"/>
        <AbilArray index="1" Link="stop"/>
        <AbilArray Link="attack"/>
        <AbilArray Link="PrologueVoidArmor"/>
        <AbilArray Link="PrologueVoidArmor2"/>
        <BehaviorArray index="0" Link="DamageBASELINE"/>
        <BehaviorArray Link="DamageUP"/>
        <TurretArray value="FreeRotate"/>
        <WeaponArray Link="Diamondback" Turret="FreeRotate"/>
        <CardLayouts index="0">
            <LayoutButtons index="0" Face="CancelBuilding" AbilCmd="BuildInProgress,Cancel" Column="4"/>
            <LayoutButtons index="1" Face="Stop" AbilCmd="stop,Stop" Row="0" Column="1"/>
            <LayoutButtons Face="AttackBuilding" Type="AbilCmd" AbilCmd="attack,Execute" Row="0" Column="4"/>
            <LayoutButtons Face="PrologueVoidArmor" Type="AbilCmd" AbilCmd="PrologueVoidArmor,Execute" Row="2" Column="0"/>
            <LayoutButtons Face="PrologueVoidArmor2" Type="AbilCmd" AbilCmd="PrologueVoidArmor2,Execute" Row="2" Column="1"/>
        </CardLayouts>
        <Footprint value="Footprint2x2"/>
        <PlacementFootprint value="Footprint2x2"/>
    </CUnit>
    <CUnit id="SupplyDepot">
        <FlagArray index="Uncloakable" value="1"/>
        <FlagArray index="Invulnerable" value="1"/>
        <Attributes index="Mechanical" value="0"/>
        <LifeStart value="65536"/>
        <LifeMax value="65536"/>
        <LifeArmor value="0"/>
        <ShieldsStart value="16"/>
        <ShieldsMax value="16"/>
        <ShieldRegenRate value="1"/>
        <ShieldArmorName value="Unit/ShieldArmorName/QuadShields"/>
        <ShieldArmorTip value="Unit/ShieldArmorName/QuadShieldsTip"/>
        <CardLayouts index="0">
            <LayoutButtons index="2" removed="1"/>
            <LayoutButtons index="3" removed="1"/>
        </CardLayouts>
        <Footprint value="Footprint3x3"/>
        <PlacementFootprint value="Footprint3x3"/>
        <ScoreMake value="0"/>
        <ScoreKill value="0"/>
        <KillDisplay value="Never"/>
        <RankDisplay value="Never"/>
    </CUnit>
    <CUnit id="SupplyDepotLowered">
        <FlagArray index="Unselectable" value="1"/>
        <FlagArray index="Uncursorable" value="1"/>
        <FlagArray index="Uncloakable" value="1"/>
        <FlagArray index="Unradarable" value="1"/>
        <FlagArray index="Invulnerable" value="1"/>
        <Attributes index="Mechanical" value="0"/>
        <LifeStart value="65536"/>
        <LifeMax value="65536"/>
        <LifeArmor value="0"/>
        <ShieldsStart value="16"/>
        <ShieldsMax value="16"/>
        <ShieldRegenRate value="0.125"/>
        <ShieldArmorName value="Unit/ShieldArmorName/QuadShields"/>
        <Food value="0"/>
        <CardLayouts index="0">
            <LayoutButtons index="0" Face="" Type="Undefined" AbilCmd=""/>
        </CardLayouts>
        <Footprint value="Footprint3x3"/>
        <Description value="Button/Tooltip/SupplyDepot"/>
    </CUnit>
</Catalog>
